dingosdk.cpython-310-x86_64-linux-gnu.so
dingosdk-0.1.0.dist-info/top_level.txt
dingosdk-0.1.0.dist-info/RECORD
dingosdk-0.1.0.dist-info/WHEEL
dingosdk-0.1.0.dist-info/METADATA
dingosdk-0.1.0.dist-info/LICENSE
