Metadata-Version: 2.1
Name: dingosdk
Version: 0.1.0
Summary: dingo-store python sdk
Author: DingoDB
Author-email: dingodb@zetyun.com
Requires-Python: >=3.9
License-File: LICENSE
